{
    "data_statistics": {
        "total_image_num": 10,
        "ng_image_num": 10,
        "total_instance_num": 159,
        "image_statistics_by_calss_name": {
            "BDG": 6,
            "FM": 10,
            "NG": 10,
            "BD": 2,
            "AUR": 4,
            "SN_R": 2,
            "BS_White": 2,
            "MB": 1,
            "MAB": 2,
            "Others": 1
        },
        "instance_statistics_by_calss_name": {
            "BDG": 17,
            "FM": 110,
            "BD": 6,
            "AUR": 9,
            "MAB": 3,
            "BS_White": 9,
            "SN_R": 3,
            "MB": 1,
            "Others": 1
        }
    },
    "record": [
        {
            "info": {
                "uuid": "14f63e1c86d1389b8b0d89ec21cad96d",
                "image_path": "changdian/2022-01-27/attention/normal/1PxM/MPS-ST3099R5-UBM/MP2112712A/2AI05QUM2/HJB169-19-G6/raw__MP2112712A_HJB169-19-G6_UBM_46_1_1.jpg",
                "height": 600,
                "width": 600
            },
            "instances": [
                {
                    "uuid": "3d46dce7a79399df0c405063434dd4bb",
                    "distribution": "3.321942e-02,0,0,0,0,3.321942e-02,0,0,0,0,0,0,0,0",
                    "shape_type": "polygon",
                    "points": "263.612122+286.460571,263.612122+306.581787,282.983337+306.581787,282.983337+286.460571,263.612122+306.581787"
                },
                {
                    "uuid": "486a12036ccd933af4ec125f18ffc1d4",
                    "distribution": "2.625498e-02,0,0,0,0,2.625498e-02,0,0,0,0,0,0,0,0",
                    "shape_type": "polygon",
                    "points": "253.731232+286.179291,253.731232+307.726501,274.127289+307.726501,274.127289+286.179291,253.731232+307.726501"
                },
                {
                    "uuid": "b834cd47b0b6f5dea84c7ab1460f072b",
                    "distribution": "2.512718e-02,0,0,0,0,2.512718e-02,0,0,0,0,0,0,0,0",
                    "shape_type": "polygon",
                    "points": "273.495636+287.101868,273.495636+305.554565,291.637268+305.554565,291.637268+287.101868,273.495636+305.554565"
                },
                {
                    "uuid": "3947f5dfb237fb0210b653b9adaa0ad0",
                    "distribution": "1.819342e-02,0,0,0,0,1.819342e-02,0,0,0,0,0,0,0,0",
                    "shape_type": "polygon",
                    "points": "283.756470+288.525909,283.756470+305.080872,299.666260+305.080872,299.666260+288.525909,283.756470+305.080872"
                },
                {
                    "uuid": "31ace629f0f3684a1c36726947e944a3",
                    "distribution": "1.754570e-02,0,0,0,0,1.754570e-02,0,0,0,0,0,0,0,0",
                    "shape_type": "polygon",
                    "points": "262.337738+278.728760,262.337738+302.211395,283.628906+302.211395,283.628906+278.728760,262.337738+302.211395"
                },
                {
                    "uuid": "23d858e04a936e4c98d7c09c8bb1d880",
                    "distribution": "1.620616e-02,0,0,0,0,1.620616e-02,0,0,0,0,0,0,0,0",
                    "shape_type": "polygon",
                    "points": "251.727112+276.534149,251.727112+302.420959,275.620697+302.420959,275.620697+276.534149,251.727112+302.420959"
                },
                {
                    "uuid": "3338d05243ea6cb95e227b1e9b1e12da",
                    "distribution": "1.187160e-02,0,0,0,0,1.187160e-02,0,0,0,0,0,0,0,0",
                    "shape_type": "polygon",
                    "points": "262.636169+291.215424,262.636169+315.367218,283.134705+315.367218,283.134705+291.215424,262.636169+315.367218"
                },
                {
                    "uuid": "eb37209a5d1464dc100f5abf48bfd419",
                    "distribution": "9.982379e-03,0,0,0,0,9.982379e-03,0,0,0,0,0,0,0,0",
                    "shape_type": "polygon",
                    "points": "272.806458+291.102081,272.806458+313.916138,292.825836+313.916138,292.825836+291.102081,272.806458+313.916138"
                },
                {
                    "uuid": "e27f2d0d50c0890a324aee6956650aa2",
                    "distribution": "1.023294e-01,0,0,0,0,0,1.023294e-01,0,0,0,0,0,0,0",
                    "shape_type": "polygon",
                    "points": "290.898102+289.695404,290.898102+305.195831,305.457886+305.195831,305.457886+289.695404,290.898102+305.195831"
                },
                {
                    "uuid": "b52a946567fc07cb0dc13a242adcda33",
                    "distribution": "9.593062e-02,0,0,0,0,0,9.593062e-02,0,0,0,0,0,0,0",
                    "shape_type": "polygon",
                    "points": "263.612122+286.460571,263.612122+306.581787,282.983337+306.581787,282.983337+286.460571,263.612122+306.581787"
                },
                {
                    "uuid": "00829dedc717cd189ca4a95f8fd65999",
                    "distribution": "8.980301e-02,0,0,0,0,0,8.980301e-02,0,0,0,0,0,0,0",
                    "shape_type": "polygon",
                    "points": "273.495636+287.101868,273.495636+305.554565,291.637268+305.554565,291.637268+287.101868,273.495636+305.554565"
                },
                {
                    "uuid": "acffa19c243959980fe84fe966f85a6f",
                    "distribution": "8.316973e-02,0,0,0,0,0,8.316973e-02,0,0,0,0,0,0,0",
                    "shape_type": "polygon",
                    "points": "283.756470+288.525909,283.756470+305.080872,299.666260+305.080872,299.666260+288.525909,283.756470+305.080872"
                },
                {
                    "uuid": "314b51a2dfdc16d08baa59cb01fc8d00",
                    "distribution": "5.748554e-02,0,0,0,0,0,5.748554e-02,0,0,0,0,0,0,0",
                    "shape_type": "polygon",
                    "points": "253.731232+286.179291,253.731232+307.726501,274.127289+307.726501,274.127289+286.179291,253.731232+307.726501"
                },
                {
                    "uuid": "9360e69eca99bbd87a0d1d658cb0ca97",
                    "distribution": "4.419293e-02,0,0,0,0,0,4.419293e-02,0,0,0,0,0,0,0",
                    "shape_type": "polygon",
                    "points": "100.018394+366.389130,100.018394+385.597198,120.033035+385.597198,120.033035+366.389130,100.018394+385.597198"
                },
                {
                    "uuid": "8ea7e177c5ce118cf69f87612afb22ca",
                    "distribution": "4.233322e-02,0,0,0,0,0,4.233322e-02,0,0,0,0,0,0,0",
                    "shape_type": "polygon",
                    "points": "262.337738+278.728760,262.337738+302.211395,283.628906+302.211395,283.628906+278.728760,262.337738+302.211395"
                },
                {
                    "uuid": "e216a7606851ceea9ef81726b727ddaf",
                    "distribution": "2.937097e-02,0,0,0,0,0,2.937097e-02,0,0,0,0,0,0,0",
                    "shape_type": "polygon",
                    "points": "251.727112+276.534149,251.727112+302.420959,275.620697+302.420959,275.620697+276.534149,251.727112+302.420959"
                },
                {
                    "uuid": "15f4faee68398b281b7a3ffc8db447d7",
                    "distribution": "2.511505e-02,0,0,0,0,0,2.511505e-02,0,0,0,0,0,0,0",
                    "shape_type": "polygon",
                    "points": "272.425690+280.912292,272.425690+302.002838,291.617950+302.002838,291.617950+280.912292,272.425690+302.002838"
                },
                {
                    "uuid": "b769d728e2a83603b5a75b80ce526ffb",
                    "distribution": "1.825572e-02,0,0,0,0,0,1.825572e-02,0,0,0,0,0,0,0",
                    "shape_type": "polygon",
                    "points": "262.636169+291.215424,262.636169+315.367218,283.134705+315.367218,283.134705+291.215424,262.636169+315.367218"
                },
                {
                    "uuid": "1f7fe0c900669199f0860ff0f17700f9",
                    "distribution": "1.794807e-02,0,0,0,0,0,1.794807e-02,0,0,0,0,0,0,0",
                    "shape_type": "polygon",
                    "points": "290.083344+283.066498,290.083344+302.180176,306.485870+302.180176,306.485870+283.066498,290.083344+302.180176"
                },
                {
                    "uuid": "13516650af86d78e70c14230952195fb",
                    "distribution": "1.671791e-02,0,0,0,0,0,1.671791e-02,0,0,0,0,0,0,0",
                    "shape_type": "polygon",
                    "points": "297.208954+289.575684,297.208954+306.073273,314.415222+306.073273,314.415222+289.575684,297.208954+306.073273"
                },
                {
                    "uuid": "544e09b8704153e734d3fd96ccff197e",
                    "distribution": "1.612526e-02,0,0,0,0,0,1.612526e-02,0,0,0,0,0,0,0",
                    "shape_type": "polygon",
                    "points": "291.172058+293.789581,291.172058+311.833038,306.639648+311.833038,306.639648+293.789581,291.172058+311.833038"
                },
                {
                    "uuid": "b113fd4e11b337dfa2ec7b13503332c5",
                    "distribution": "1.561109e-02,0,0,0,0,0,1.561109e-02,0,0,0,0,0,0,0",
                    "shape_type": "polygon",
                    "points": "282.744049+282.707611,282.744049+302.144440,299.818604+302.144440,299.818604+282.707611,282.744049+302.144440"
                },
                {
                    "uuid": "6cd42bd185f09e40f54af9596cffe3c6",
                    "distribution": "1.546432e-02,0,0,0,0,0,1.546432e-02,0,0,0,0,0,0,0",
                    "shape_type": "polygon",
                    "points": "272.806458+291.102081,272.806458+313.916138,292.825836+313.916138,292.825836+291.102081,272.806458+313.916138"
                },
                {
                    "uuid": "4a93290dde434575ab0100b0fe23209e",
                    "distribution": "1.275371e-02,0,0,0,0,0,1.275371e-02,0,0,0,0,0,0,0",
                    "shape_type": "polygon",
                    "points": "283.416138+292.145752,283.416138+312.335999,301.035797+312.335999,301.035797+292.145752,283.416138+312.335999"
                }
            ]
        },
        {
            "info": {
                "uuid": "d30325693fcb340e43c014bd5e61c242",
                "image_path": "changdian/2022-01-27/attention/normal/1PxM/MPS-ST3099R5-UBM/MP2112720A/2AI05QUM2/HJB297-17-A4/raw__MP2112720A_HJB297-17-A4_UBM_39_1_1.jpg",
                "height": 600,
                "width": 600
            },
            "instances": [
                {
                    "uuid": "24cd0b060a4f871762e9369fe81535d3",
                    "distribution": "8.473802e-02,0,0,0,0,8.473802e-02,0,0,0,0,0,0,0,0",
                    "shape_type": "polygon",
                    "points": "290.647522+289.120819,290.647522+307.366455,308.572327+307.366455,308.572327+289.120819,290.647522+307.366455"
                },
                {
                    "uuid": "a48e094bdb8b3e1d60b7d3caac582c75",
                    "distribution": "8.672505e-03,0,0,0,0,8.672505e-03,0,0,0,0,0,0,0,0",
                    "shape_type": "polygon",
                    "points": "292.132294+290.643616,292.132294+312.972778,314.147858+312.972778,314.147858+290.643616,292.132294+312.972778"
                },
                {
                    "uuid": "f2b6291b1a6675d36117452d603b6aba",
                    "distribution": "7.999916e-03,0,0,0,0,7.999916e-03,0,0,0,0,0,0,0,0",
                    "shape_type": "polygon",
                    "points": "284.462006+283.324371,284.462006+305.346222,307.729950+305.346222,307.729950+283.324371,284.462006+305.346222"
                },
                {
                    "uuid": "8787c91de4cec23e0375132702e77203",
                    "distribution": "5.270470e-03,0,0,0,0,5.270470e-03,0,0,0,0,0,0,0,0",
                    "shape_type": "polygon",
                    "points": "285.457611+289.897247,285.457611+312.472931,308.842651+312.472931,308.842651+289.897247,285.457611+312.472931"
                },
                {
                    "uuid": "5ccf0b14709b5d5303c267b1f4899b35",
                    "distribution": "3.321461e-01,0,0,0,0,0,3.321461e-01,0,0,0,0,0,0,0",
                    "shape_type": "polygon",
                    "points": "290.647522+289.120819,290.647522+307.366455,308.572327+307.366455,308.572327+289.120819,290.647522+307.366455"
                },
                {
                    "uuid": "a0fb0eebe05cb3821106738e21e3269f",
                    "distribution": "3.051849e-02,0,0,0,0,0,3.051849e-02,0,0,0,0,0,0,0",
                    "shape_type": "polygon",
                    "points": "289.672150+295.284363,289.672150+321.029663,311.540070+321.029663,311.540070+295.284363,289.672150+321.029663"
                },
                {
                    "uuid": "64a6d6505e6a1ba10431784f999791f6",
                    "distribution": "2.247648e-02,0,0,0,0,0,2.247648e-02,0,0,0,0,0,0,0",
                    "shape_type": "polygon",
                    "points": "327.056610+269.170715,327.056610+291.564911,347.684937+291.564911,347.684937+269.170715,327.056610+291.564911"
                },
                {
                    "uuid": "1559eada9fc15684d67cd78ca0a716a6",
                    "distribution": "2.167043e-02,0,0,0,0,0,2.167043e-02,0,0,0,0,0,0,0",
                    "shape_type": "polygon",
                    "points": "292.132294+290.643616,292.132294+312.972778,314.147858+312.972778,314.147858+290.643616,292.132294+312.972778"
                },
                {
                    "uuid": "46eb1f6e0fb86e95fd65bb12c53d1907",
                    "distribution": "1.844237e-02,0,0,0,0,0,1.844237e-02,0,0,0,0,0,0,0",
                    "shape_type": "polygon",
                    "points": "284.462006+283.324371,284.462006+305.346222,307.729950+305.346222,307.729950+283.324371,284.462006+305.346222"
                },
                {
                    "uuid": "d19a8f3c929ac72efa3c05e006312e4f",
                    "distribution": "1.700334e-02,0,0,0,0,0,1.700334e-02,0,0,0,0,0,0,0",
                    "shape_type": "polygon",
                    "points": "293.799377+296.548065,293.799377+323.249420,317.910065+323.249420,317.910065+296.548065,293.799377+323.249420"
                },
                {
                    "uuid": "5e9c1adfae0468059f061958d25392f1",
                    "distribution": "1.487578e-02,0,0,0,0,0,1.487578e-02,0,0,0,0,0,0,0",
                    "shape_type": "polygon",
                    "points": "336.219696+269.345093,336.219696+291.323425,357.589661+291.323425,357.589661+269.345093,336.219696+291.323425"
                },
                {
                    "uuid": "5e9cb33aed2d7a365127d46370d248f0",
                    "distribution": "1.192898e-02,0,0,0,0,0,1.192898e-02,0,0,0,0,0,0,0",
                    "shape_type": "polygon",
                    "points": "285.457611+289.897247,285.457611+312.472931,308.842651+312.472931,308.842651+289.897247,285.457611+312.472931"
                },
                {
                    "uuid": "bfb46d009966452a9bbbc7c1859806d6",
                    "distribution": "8.628229e-03,0,0,0,0,0,8.628229e-03,0,0,0,0,0,0,0",
                    "shape_type": "polygon",
                    "points": "292.697601+284.242096,292.697601+305.248260,315.097748+305.248260,315.097748+284.242096,292.697601+305.248260"
                }
            ]
        },
        {
            "info": {
                "uuid": "59fe019ce0722fad5ae2b6fcba9b68a9",
                "image_path": "changdian/2022-01-27/attention/normal/1PxM/MPS-ST3099R5-UBM/MP2112712A/2AI05QUM2/HJB169-04-F3/raw__MP2112712A_HJB169-04-F3_UBM_9_1_1.jpg",
                "height": 600,
                "width": 600
            },
            "instances": [
                {
                    "uuid": "73db27eb3785d6523b6dfa32b1dcf693",
                    "distribution": "6.946061e-02,0,0,6.946061e-02,0,0,0,0,0,0,0,0,0,0",
                    "shape_type": "polygon",
                    "points": "298.721008+344.640137,298.721008+406.674133,368.510956+406.674133,368.510956+344.640137,298.721008+406.674133"
                },
                {
                    "uuid": "176c0c5db43c2c8dcea1481a5fb7ecdd",
                    "distribution": "4.886881e-02,0,0,4.886881e-02,0,0,0,0,0,0,0,0,0,0",
                    "shape_type": "polygon",
                    "points": "334.126556+92.418716,334.126556+164.304535,412.215668+164.304535,412.215668+92.418716,334.126556+164.304535"
                },
                {
                    "uuid": "7742c780b00959b3b39d3c788db79117",
                    "distribution": "1.636875e-01,0,0,0,1.636875e-01,0,0,0,0,0,0,0,0,0",
                    "shape_type": "polygon",
                    "points": "298.852539+344.127411,298.852539+406.235840,368.819275+406.235840,368.819275+344.127411,298.852539+406.235840"
                },
                {
                    "uuid": "78cf993e12dc3172b2ea75858cf288a5",
                    "distribution": "4.983909e-02,0,0,0,4.983909e-02,0,0,0,0,0,0,0,0,0",
                    "shape_type": "polygon",
                    "points": "525.648499+343.513855,525.648499+408.373810,596.167114+408.373810,596.167114+343.513855,525.648499+408.373810"
                },
                {
                    "uuid": "cb75942628201fd17378a5ca79195c49",
                    "distribution": "1.226363e-01,0,0,0,0,0,1.226363e-01,0,0,0,0,0,0,0",
                    "shape_type": "polygon",
                    "points": "403.619690+290.196503,403.619690+303.517700,420.052765+303.517700,420.052765+290.196503,403.619690+303.517700"
                },
                {
                    "uuid": "2d35b1dfad0a400fe3d4040272b34009",
                    "distribution": "1.055183e-01,0,0,0,0,0,1.055183e-01,0,0,0,0,0,0,0",
                    "shape_type": "polygon",
                    "points": "179.181534+289.541595,179.181534+302.393951,194.778046+302.393951,194.778046+289.541595,179.181534+302.393951"
                },
                {
                    "uuid": "34297d067761be0480d55f155b5f4f54",
                    "distribution": "5.714811e-02,0,0,0,0,0,5.714811e-02,0,0,0,0,0,0,0",
                    "shape_type": "polygon",
                    "points": "290.264191+289.117584,290.264191+302.325317,306.602844+302.325317,306.602844+289.117584,290.264191+302.325317"
                },
                {
                    "uuid": "dd072befda386e0798eac92a46bfcb13",
                    "distribution": "4.457405e-02,0,0,0,0,0,4.457405e-02,0,0,0,0,0,0,0",
                    "shape_type": "polygon",
                    "points": "395.313446+289.870850,395.313446+303.553955,413.946411+303.553955,413.946411+289.870850,395.313446+303.553955"
                },
                {
                    "uuid": "cbf58c4b284fba82b23da451ed4e607e",
                    "distribution": "4.199314e-02,0,0,0,0,0,4.199314e-02,0,0,0,0,0,0,0",
                    "shape_type": "polygon",
                    "points": "184.719666+289.395660,184.719666+302.706726,202.054001+302.706726,202.054001+289.395660,184.719666+302.706726"
                },
                {
                    "uuid": "517dfb1b75885ddb395957bcaef103ae",
                    "distribution": "3.835817e-02,0,0,0,0,0,3.835817e-02,0,0,0,0,0,0,0",
                    "shape_type": "polygon",
                    "points": "410.337189+289.808807,410.337189+303.804596,427.904449+303.804596,427.904449+289.808807,410.337189+303.804596"
                },
                {
                    "uuid": "15a58994772bd0c6f788de2fe0c96543",
                    "distribution": "3.806309e-02,0,0,0,0,0,3.806309e-02,0,0,0,0,0,0,0",
                    "shape_type": "polygon",
                    "points": "283.427795+288.938721,283.427795+302.556519,300.585022+302.556519,300.585022+288.938721,283.427795+302.556519"
                },
                {
                    "uuid": "552e7b09e884d931d7ecac9f5a160cd5",
                    "distribution": "3.490917e-02,0,0,0,0,0,3.490917e-02,0,0,0,0,0,0,0",
                    "shape_type": "polygon",
                    "points": "384.506317+289.270813,384.506317+303.338593,404.491272+303.338593,404.491272+289.270813,384.506317+303.338593"
                },
                {
                    "uuid": "1d63212ab72f724ac2b644bbfb077851",
                    "distribution": "3.437126e-02,0,0,0,0,0,3.437126e-02,0,0,0,0,0,0,0",
                    "shape_type": "polygon",
                    "points": "171.472076+289.274506,171.472076+302.788940,188.866028+302.788940,188.866028+289.274506,171.472076+302.788940"
                },
                {
                    "uuid": "de339b10890f1267b43b762f35520366",
                    "distribution": "3.413595e-02,0,0,0,0,0,3.413595e-02,0,0,0,0,0,0,0",
                    "shape_type": "polygon",
                    "points": "328.708344+289.169159,328.708344+303.085602,346.499268+303.085602,346.499268+289.169159,328.708344+303.085602"
                },
                {
                    "uuid": "0cabc694018294a3c7563772fb16ac56",
                    "distribution": "3.088799e-02,0,0,0,0,0,3.088799e-02,0,0,0,0,0,0,0",
                    "shape_type": "polygon",
                    "points": "375.345398+288.938202,375.345398+303.111359,395.171417+303.111359,395.171417+288.938202,375.345398+303.111359"
                },
                {
                    "uuid": "164ca85dddc2752f080b93f1c03b6d63",
                    "distribution": "2.843584e-02,0,0,0,0,0,2.843584e-02,0,0,0,0,0,0,0",
                    "shape_type": "polygon",
                    "points": "337.866180+289.256378,337.866180+302.866669,355.416901+302.866669,355.416901+289.256378,337.866180+302.866669"
                },
                {
                    "uuid": "cdc6b89ea14738fef4b1b7c3dbc5a076",
                    "distribution": "2.467462e-02,0,0,0,0,0,2.467462e-02,0,0,0,0,0,0,0",
                    "shape_type": "polygon",
                    "points": "346.848816+289.174927,346.848816+302.732727,364.399475+302.732727,364.399475+289.174927,346.848816+302.732727"
                },
                {
                    "uuid": "1be84c734819470bd4858ec583af9506",
                    "distribution": "2.401684e-02,0,0,0,0,0,2.401684e-02,0,0,0,0,0,0,0",
                    "shape_type": "polygon",
                    "points": "298.039612+288.948425,298.039612+302.821411,316.301453+302.821411,316.301453+288.948425,298.039612+302.821411"
                },
                {
                    "uuid": "86647abeab669246223cdf0364a4f1a3",
                    "distribution": "2.258090e-02,0,0,0,0,0,2.258090e-02,0,0,0,0,0,0,0",
                    "shape_type": "polygon",
                    "points": "319.659943+288.712158,319.659943+303.072418,338.275604+303.072418,338.275604+288.712158,319.659943+303.072418"
                },
                {
                    "uuid": "0ae593c1e5e6c10756ad3064ececbdea",
                    "distribution": "2.130266e-02,0,0,0,0,0,2.130266e-02,0,0,0,0,0,0,0",
                    "shape_type": "polygon",
                    "points": "178.457947+284.599365,178.457947+299.325531,195.711670+299.325531,195.711670+284.599365,178.457947+299.325531"
                },
                {
                    "uuid": "f642c0f5e7473487b75ecfaa7a214440",
                    "distribution": "1.669242e-02,0,0,0,0,0,1.669242e-02,0,0,0,0,0,0,0",
                    "shape_type": "polygon",
                    "points": "309.027283+288.575745,309.027283+303.046692,328.392090+303.046692,328.392090+288.575745,309.027283+303.046692"
                },
                {
                    "uuid": "d22c51419f0b6ac2af1e5a99c2420141",
                    "distribution": "1.453558e-02,0,0,0,0,0,1.453558e-02,0,0,0,0,0,0,0",
                    "shape_type": "polygon",
                    "points": "402.875732+284.269226,402.875732+299.616669,421.136261+299.616669,421.136261+284.269226,402.875732+299.616669"
                },
                {
                    "uuid": "b06f08a840aaf80622c66c55345a3976",
                    "distribution": "1.281059e-02,0,0,0,0,0,1.281059e-02,0,0,0,0,0,0,0",
                    "shape_type": "polygon",
                    "points": "289.525635+283.896545,289.525635+298.778931,307.267639+298.778931,307.267639+283.896545,289.525635+298.778931"
                },
                {
                    "uuid": "38b21863717386147420ff89a4fdd4ee",
                    "distribution": "1.270369e-02,0,0,0,0,0,1.270369e-02,0,0,0,0,0,0,0",
                    "shape_type": "polygon",
                    "points": "140.911377+282.278076,140.911377+297.781952,158.980911+297.781952,158.980911+282.278076,140.911377+297.781952"
                },
                {
                    "uuid": "a151f8bb925c27db43ba674f8b017e49",
                    "distribution": "1.028897e-02,0,0,0,0,0,1.028897e-02,0,0,0,0,0,0,0",
                    "shape_type": "polygon",
                    "points": "184.277893+284.012146,184.277893+299.063965,203.106003+299.063965,203.106003+284.012146,184.277893+299.063965"
                },
                {
                    "uuid": "7ab72ab00975e7d0a7b4d5409c58451c",
                    "distribution": "9.654203e-03,0,0,0,0,0,9.654203e-03,0,0,0,0,0,0,0",
                    "shape_type": "polygon",
                    "points": "402.597656+293.757477,402.597656+310.619415,420.962585+310.619415,420.962585+293.757477,402.597656+310.619415"
                },
                {
                    "uuid": "be1eab7a09d9733712e5af638183cfcf",
                    "distribution": "6.760950e-03,0,0,0,0,0,6.760950e-03,0,0,0,0,0,0,0",
                    "shape_type": "polygon",
                    "points": "170.491074+284.350891,170.491074+299.534607,189.340958+299.534607,189.340958+284.350891,170.491074+299.534607"
                }
            ]
        },
        {
            "info": {
                "uuid": "b87377146ea89366a7cdbb61cc38efd6",
                "image_path": "changdian/2022-01-27/attention/normal/1PxM/MPS-SM3519ZR8-UBM/NP2142533A/2AI05BUM2/X26477-01B4/raw__X26477-01B4_X_71_Y_76_131_1.jpg",
                "height": 600,
                "width": 600
            },
            "instances": [
                {
                    "uuid": "a6df5d15614f87f9d416130c43e942d9",
                    "distribution": "5.806851e-02,5.806851e-02,0,0,0,0,0,0,0,0,0,0,0,0",
                    "shape_type": "polygon",
                    "points": "359.354492+478.715179,359.354492+550.955811,432.556976+550.955811,432.556976+478.715179,359.354492+550.955811"
                },
                {
                    "uuid": "06fd5f08d45ac54c0fbb7b50ec86cff8",
                    "distribution": "4.307274e-02,4.307274e-02,0,0,0,0,0,0,0,0,0,0,0,0",
                    "shape_type": "polygon",
                    "points": "517.927429+549.337402,517.927429+600.000000,585.142273+600.000000,585.142273+549.337402,517.927429+600.000000"
                },
                {
                    "uuid": "7a25d64330a531c9eb4ba19b51eb1008",
                    "distribution": "8.341695e-02,0,0,0,8.341695e-02,0,0,0,0,0,0,0,0,0",
                    "shape_type": "polygon",
                    "points": "355.226959+102.125267,355.226959+185.290192,436.732635+185.290192,436.732635+102.125267,355.226959+185.290192"
                },
                {
                    "uuid": "45110836c8173c7c32da5a36c4301e05",
                    "distribution": "4.135148e-02,0,0,0,4.135148e-02,0,0,0,0,0,0,0,0,0",
                    "shape_type": "polygon",
                    "points": "4.234513+262.360748,4.234513+331.875244,68.089241+331.875244,68.089241+262.360748,4.234513+331.875244"
                },
                {
                    "uuid": "763eee438b837448a9835df8d0ba120f",
                    "distribution": "3.047870e-02,0,0,0,3.047870e-02,0,0,0,0,0,0,0,0,0",
                    "shape_type": "polygon",
                    "points": "266.179993+262.185333,266.179993+331.919556,336.228210+331.919556,336.228210+262.185333,266.179993+331.919556"
                },
                {
                    "uuid": "15032c25e7b460fc30aebe70213fded5",
                    "distribution": "3.754802e-02,0,0,0,0,3.754802e-02,0,0,0,0,0,0,0,0",
                    "shape_type": "polygon",
                    "points": "78.299904+96.237511,78.299904+401.945953,480.518158+401.945953,480.518158+96.237511,78.299904+401.945953"
                },
                {
                    "uuid": "8ce3d507043a2021219a2131aac34e0e",
                    "distribution": "1.164899e-01,0,0,0,0,0,1.164899e-01,0,0,0,0,0,0,0",
                    "shape_type": "polygon",
                    "points": "275.327423+161.194229,275.327423+192.790466,314.634125+192.790466,314.634125+161.194229,275.327423+192.790466"
                },
                {
                    "uuid": "5bbc8894e403f7dd19c593d7a888ed59",
                    "distribution": "2.683596e-02,0,0,0,0,0,2.683596e-02,0,0,0,0,0,0,0",
                    "shape_type": "polygon",
                    "points": "284.524567+156.336227,284.524567+190.062180,320.678955+190.062180,320.678955+156.336227,284.524567+190.062180"
                },
                {
                    "uuid": "1ea60edebb28087bdf835beebc6ebc06",
                    "distribution": "7.909959e-01,0,0,0,0,0,0,0,7.909959e-01,0,0,0,0,0",
                    "shape_type": "polygon",
                    "points": "266.826691+263.252228,266.826691+332.566559,336.752716+332.566559,336.752716+263.252228,266.826691+332.566559"
                },
                {
                    "uuid": "b80617d0cd780e25d4be27997f3042b1",
                    "distribution": "2.680943e-01,0,0,0,0,0,0,0,2.680943e-01,0,0,0,0,0",
                    "shape_type": "polygon",
                    "points": "359.235321+478.209412,359.235321+551.859863,434.204010+551.859863,434.204010+478.209412,359.235321+551.859863"
                },
                {
                    "uuid": "fe1d19f48c414c7f8d47511d431dca50",
                    "distribution": "1.083955e-01,0,0,0,0,0,0,0,1.083955e-01,0,0,0,0,0",
                    "shape_type": "polygon",
                    "points": "517.927429+549.337402,517.927429+600.000000,585.142273+600.000000,585.142273+549.337402,517.927429+600.000000"
                },
                {
                    "uuid": "3eee139dad3173e56a3cfd816844ef30",
                    "distribution": "5.652478e-02,0,0,0,0,0,0,0,5.652478e-02,0,0,0,0,0",
                    "shape_type": "polygon",
                    "points": "355.226959+102.125267,355.226959+185.290192,436.732635+185.290192,436.732635+102.125267,355.226959+185.290192"
                },
                {
                    "uuid": "ed3e4ad41e3eb619ed10b85a36ef47c7",
                    "distribution": "1.063930e-01,0,0,0,0,0,0,0,0,1.063930e-01,0,0,0,0",
                    "shape_type": "polygon",
                    "points": "78.299904+96.237511,78.299904+401.945953,480.518158+401.945953,480.518158+96.237511,78.299904+401.945953"
                },
                {
                    "uuid": "3050fc3eb72963b707df2d7215fe6a44",
                    "distribution": "3.213944e-02,0,0,0,0,0,0,0,0,3.213944e-02,0,0,0,0",
                    "shape_type": "polygon",
                    "points": "172.325928+51.637028,172.325928+430.258331,516.382080+430.258331,516.382080+51.637028,172.325928+430.258331"
                },
                {
                    "uuid": "b96fe33910a2d2c61524de9cfbce8cc0",
                    "distribution": "7.685424e-02,0,0,0,0,0,0,0,0,0,0,7.685424e-02,0,0",
                    "shape_type": "polygon",
                    "points": "359.354492+478.715179,359.354492+550.955811,432.556976+550.955811,432.556976+478.715179,359.354492+550.955811"
                },
                {
                    "uuid": "fcd9bada071812f5dfc51da204382c18",
                    "distribution": "5.878732e-02,0,0,0,0,0,0,0,0,0,0,0,0,5.878732e-02",
                    "shape_type": "polygon",
                    "points": "517.927429+549.337402,517.927429+600.000000,585.142273+600.000000,585.142273+549.337402,517.927429+600.000000"
                }
            ]
        },
        {
            "info": {
                "uuid": "98139f4e6532c8abe7d75254cab58244",
                "image_path": "changdian/2022-01-27/attention/normal/1PxM/MPS-ST3099R5-UBM/MP2112707A/2AI05QUM2/HJA520-21-B1/raw__MP2112707A_HJA520-21-B1_UBM_30_1_1.jpg",
                "height": 600,
                "width": 600
            },
            "instances": [
                {
                    "uuid": "fc12367cdf43ef35e33f8bb295a54798",
                    "distribution": "7.993133e-02,0,0,0,0,0,7.993133e-02,0,0,0,0,0,0,0",
                    "shape_type": "polygon",
                    "points": "402.077332+186.553268,402.077332+205.746826,425.017212+205.746826,425.017212+186.553268,402.077332+205.746826"
                },
                {
                    "uuid": "2060b084066c53dee272f92f2a456df3",
                    "distribution": "5.265449e-02,0,0,0,0,0,5.265449e-02,0,0,0,0,0,0,0",
                    "shape_type": "polygon",
                    "points": "252.566269+289.613312,252.566269+311.334839,272.863953+311.334839,272.863953+289.613312,252.566269+311.334839"
                },
                {
                    "uuid": "4fdb6fc5947f027aded68cb46520e184",
                    "distribution": "4.635885e-02,0,0,0,0,0,4.635885e-02,0,0,0,0,0,0,0",
                    "shape_type": "polygon",
                    "points": "404.494476+190.052887,404.494476+210.341156,428.566986+210.341156,428.566986+190.052887,404.494476+210.341156"
                },
                {
                    "uuid": "72e3bfd5989968f38d7591cdb0165483",
                    "distribution": "4.616714e-02,0,0,0,0,0,4.616714e-02,0,0,0,0,0,0,0",
                    "shape_type": "polygon",
                    "points": "177.140213+265.066467,177.140213+291.476532,197.632141+291.476532,197.632141+265.066467,177.140213+291.476532"
                },
                {
                    "uuid": "520f42fef098596087f681b8fa9fa717",
                    "distribution": "4.192202e-02,0,0,0,0,0,4.192202e-02,0,0,0,0,0,0,0",
                    "shape_type": "polygon",
                    "points": "299.087891+288.003418,299.087891+305.287201,319.545441+305.287201,319.545441+288.003418,299.087891+305.287201"
                },
                {
                    "uuid": "d85a0de31eae8588e4550f8c0d0cdd63",
                    "distribution": "3.276469e-02,0,0,0,0,0,3.276469e-02,0,0,0,0,0,0,0",
                    "shape_type": "polygon",
                    "points": "308.057220+287.781616,308.057220+305.440796,327.803619+305.440796,327.803619+287.781616,308.057220+305.440796"
                },
                {
                    "uuid": "bfe6187bf79c6af57b1d13a713b38f01",
                    "distribution": "3.266372e-02,0,0,0,0,0,3.266372e-02,0,0,0,0,0,0,0",
                    "shape_type": "polygon",
                    "points": "250.507050+292.737885,250.507050+320.132263,272.676605+320.132263,272.676605+292.737885,250.507050+320.132263"
                },
                {
                    "uuid": "9777fae6f4fd58499e16d4cc5e7e5bae",
                    "distribution": "3.222972e-02,0,0,0,0,0,3.222972e-02,0,0,0,0,0,0,0",
                    "shape_type": "polygon",
                    "points": "247.695633+296.886505,247.695633+330.363220,272.843445+330.363220,272.843445+296.886505,247.695633+330.363220"
                },
                {
                    "uuid": "149c0ee946c46e2bc7fe2c22845e481e",
                    "distribution": "3.015132e-02,0,0,0,0,0,3.015132e-02,0,0,0,0,0,0,0",
                    "shape_type": "polygon",
                    "points": "177.074219+270.733002,177.074219+300.793365,198.612000+300.793365,198.612000+270.733002,177.074219+300.793365"
                },
                {
                    "uuid": "00f8244664fada8375c104d416aba971",
                    "distribution": "2.875355e-02,0,0,0,0,0,2.875355e-02,0,0,0,0,0,0,0",
                    "shape_type": "polygon",
                    "points": "404.059387+400.342224,404.059387+420.070099,423.990509+420.070099,423.990509+400.342224,404.059387+420.070099"
                },
                {
                    "uuid": "122c26e9834f6132448f13bdcd99b899",
                    "distribution": "2.819716e-02,0,0,0,0,0,2.819716e-02,0,0,0,0,0,0,0",
                    "shape_type": "polygon",
                    "points": "252.169479+362.729828,252.169479+380.763855,270.207092+380.763855,270.207092+362.729828,252.169479+380.763855"
                },
                {
                    "uuid": "d79e5c93fd2148fde31265f4c9634354",
                    "distribution": "2.800476e-02,0,0,0,0,0,2.800476e-02,0,0,0,0,0,0,0",
                    "shape_type": "polygon",
                    "points": "289.288147+288.562897,289.288147+305.648560,310.241119+305.648560,310.241119+288.562897,289.288147+305.648560"
                },
                {
                    "uuid": "6bca6972436320948f79118b7e2dc6e0",
                    "distribution": "2.675485e-02,0,0,0,0,0,2.675485e-02,0,0,0,0,0,0,0",
                    "shape_type": "polygon",
                    "points": "245.014465+362.958221,245.014465+380.943420,263.341125+380.943420,263.341125+362.958221,245.014465+380.943420"
                },
                {
                    "uuid": "7f84ecd9f765e95178e6d3c2f57e9833",
                    "distribution": "2.408880e-02,0,0,0,0,0,2.408880e-02,0,0,0,0,0,0,0",
                    "shape_type": "polygon",
                    "points": "279.562164+289.135590,279.562164+305.949982,299.447632+305.949982,299.447632+289.135590,279.562164+305.949982"
                },
                {
                    "uuid": "f8670218120a242ab7c1f5a6878b292a",
                    "distribution": "2.241777e-02,0,0,0,0,0,2.241777e-02,0,0,0,0,0,0,0",
                    "shape_type": "polygon",
                    "points": "410.662476+400.152252,410.662476+419.418304,431.585968+419.418304,431.585968+400.152252,410.662476+419.418304"
                },
                {
                    "uuid": "8db340c285017f30505c20ebe027e92f",
                    "distribution": "2.001689e-02,0,0,0,0,0,2.001689e-02,0,0,0,0,0,0,0",
                    "shape_type": "polygon",
                    "points": "259.666779+290.481720,259.666779+308.606415,278.812500+308.606415,278.812500+290.481720,259.666779+308.606415"
                },
                {
                    "uuid": "64f9be3d10744018635ead672a55e61e",
                    "distribution": "1.586916e-02,0,0,0,0,0,1.586916e-02,0,0,0,0,0,0,0",
                    "shape_type": "polygon",
                    "points": "182.890930+271.532806,182.890930+303.028687,206.671417+303.028687,206.671417+271.532806,182.890930+303.028687"
                }
            ]
        },
        {
            "info": {
                "uuid": "44f08433528a9b4a6144f2e16dbdeb2b",
                "image_path": "changdian/2022-01-27/attention/normal/1PxM/MPS-ST3099R5-UBM/MP2112712A/2AI05QUM2/HJB169-02-A5/raw__MP2112712A_HJB169-02-A5_UBM_20_1_1.jpg",
                "height": 600,
                "width": 600
            },
            "instances": [
                {
                    "uuid": "cedf95fdcf2db5eb3c98f599b6ab41ff",
                    "distribution": "4.365104e-02,4.365104e-02,0,0,0,0,0,0,0,0,0,0,0,0",
                    "shape_type": "polygon",
                    "points": "263.368378+341.396454,263.368378+405.907806,334.073639+405.907806,334.073639+341.396454,263.368378+405.907806"
                },
                {
                    "uuid": "13547d915b681224258b46b9d62aaa31",
                    "distribution": "1.195040e-01,0,0,1.195040e-01,0,0,0,0,0,0,0,0,0,0",
                    "shape_type": "polygon",
                    "points": "134.611282+85.940689,134.611282+163.802658,217.101257+163.802658,217.101257+85.940689,134.611282+163.802658"
                },
                {
                    "uuid": "99e2026272c850d5c15544cf80e049b3",
                    "distribution": "6.664923e-02,0,0,6.664923e-02,0,0,0,0,0,0,0,0,0,0",
                    "shape_type": "polygon",
                    "points": "258.327179+89.343521,258.327179+163.918121,340.778656+163.918121,340.778656+89.343521,258.327179+163.918121"
                },
                {
                    "uuid": "934f01f5281811ce946fcdbc325bb449",
                    "distribution": "6.470075e-02,0,0,6.470075e-02,0,0,0,0,0,0,0,0,0,0",
                    "shape_type": "polygon",
                    "points": "263.368378+341.396454,263.368378+405.907806,334.073639+405.907806,334.073639+341.396454,263.368378+405.907806"
                },
                {
                    "uuid": "245818d1c481925cde94f09c2d34db32",
                    "distribution": "2.795159e-02,0,0,2.795159e-02,0,0,0,0,0,0,0,0,0,0",
                    "shape_type": "polygon",
                    "points": "156.168076+82.752197,156.168076+152.912003,224.242722+152.912003,224.242722+82.752197,156.168076+152.912003"
                },
                {
                    "uuid": "b7ce73a66720b728a89ae97970919337",
                    "distribution": "7.273903e-02,0,0,0,7.273903e-02,0,0,0,0,0,0,0,0,0",
                    "shape_type": "polygon",
                    "points": "134.386917+86.310211,134.386917+164.214706,217.396637+164.214706,217.396637+86.310211,134.386917+164.214706"
                },
                {
                    "uuid": "f8284ef4b9ea5c1144c2f97ee3460294",
                    "distribution": "6.425492e-02,0,0,0,6.425492e-02,0,0,0,0,0,0,0,0,0",
                    "shape_type": "polygon",
                    "points": "263.368378+341.396454,263.368378+405.907806,334.073639+405.907806,334.073639+341.396454,263.368378+405.907806"
                },
                {
                    "uuid": "903f598b6148a7363e8b79621c1d8197",
                    "distribution": "3.986906e-02,0,0,0,0,0,3.986906e-02,0,0,0,0,0,0,0",
                    "shape_type": "polygon",
                    "points": "293.173676+287.939301,293.173676+303.955261,308.468475+303.955261,308.468475+287.939301,293.173676+303.955261"
                },
                {
                    "uuid": "236faadae488e7752e87a11bd363cb06",
                    "distribution": "2.964226e-02,0,0,0,0,0,2.964226e-02,0,0,0,0,0,0,0",
                    "shape_type": "polygon",
                    "points": "182.643539+87.979675,182.643539+138.276382,222.982056+138.276382,222.982056+87.979675,182.643539+138.276382"
                },
                {
                    "uuid": "2a63f77ae2fbac8b981ecfbb984251e2",
                    "distribution": "1.547791e-02,0,0,0,0,0,1.547791e-02,0,0,0,0,0,0,0",
                    "shape_type": "polygon",
                    "points": "283.616669+287.299957,283.616669+305.014587,302.017548+305.014587,302.017548+287.299957,283.616669+305.014587"
                },
                {
                    "uuid": "1b7ccff6e99904c89afe0b1511b2b994",
                    "distribution": "1.245438e-02,0,0,0,0,0,1.245438e-02,0,0,0,0,0,0,0",
                    "shape_type": "polygon",
                    "points": "292.480774+281.329163,292.480774+298.126221,308.866638+298.126221,308.866638+281.329163,292.480774+298.126221"
                }
            ]
        },
        {
            "info": {
                "uuid": "c63f5c10a1e6059d3b9ae05fa429b3f9",
                "image_path": "changdian/2022-01-27/attention/normal/1PxM/MPS-ST3099R5-UBM/MP2112720A/2AI05QUM2/HJB297-15-D1/raw__MP2112720A_HJB297-15-D1_UBM_17_1_1.jpg",
                "height": 600,
                "width": 600
            },
            "instances": [
                {
                    "uuid": "39fe50f2da5cfd5604db0e65dcf580ee",
                    "distribution": "4.620979e-02,0,0,0,0,4.620979e-02,0,0,0,0,0,0,0,0",
                    "shape_type": "polygon",
                    "points": "284.821655+269.027588,284.821655+307.525848,334.302521+307.525848,334.302521+269.027588,284.821655+307.525848"
                },
                {
                    "uuid": "09c2b067f4e6228c42fa953f72551888",
                    "distribution": "6.088228e-01,0,0,0,0,0,6.088228e-01,0,0,0,0,0,0,0",
                    "shape_type": "polygon",
                    "points": "284.821655+269.027588,284.821655+307.525848,334.302521+307.525848,334.302521+269.027588,284.821655+307.525848"
                },
                {
                    "uuid": "8953aa42034b946460d2ea7c7741cfde",
                    "distribution": "6.605313e-02,0,0,0,0,0,6.605313e-02,0,0,0,0,0,0,0",
                    "shape_type": "polygon",
                    "points": "278.409851+273.623413,278.409851+308.340027,322.199677+308.340027,322.199677+273.623413,278.409851+308.340027"
                },
                {
                    "uuid": "089ed082708bc18ff15b5474f2b39887",
                    "distribution": "3.685023e-02,0,0,0,0,0,3.685023e-02,0,0,0,0,0,0,0",
                    "shape_type": "polygon",
                    "points": "248.535095+20.697792,248.535095+44.570690,269.980164+44.570690,269.980164+20.697792,248.535095+44.570690"
                },
                {
                    "uuid": "b3693f9ce2a77edb31cc692d8e962a91",
                    "distribution": "2.322812e-02,0,0,0,0,0,2.322812e-02,0,0,0,0,0,0,0",
                    "shape_type": "polygon",
                    "points": "297.264038+258.256836,297.264038+301.371918,345.886688+301.371918,345.886688+258.256836,297.264038+301.371918"
                }
            ]
        },
        {
            "info": {
                "uuid": "cb353fb43af7bae8c7b7bc824dbf43e8",
                "image_path": "changdian/2022-01-27/attention/normal/1PxM/MPS-ST3099R5-UBM/MP2112707A/2AI05QUM2/HJA520-21-B1/raw__MP2112707A_HJA520-21-B1_UBM_41_1_1.jpg",
                "height": 600,
                "width": 600
            },
            "instances": [
                {
                    "uuid": "b560c32efeea0d4e588d333974fac703",
                    "distribution": "1.733019e-01,0,0,0,0,0,1.733019e-01,0,0,0,0,0,0,0",
                    "shape_type": "polygon",
                    "points": "327.990265+289.885193,327.990265+305.111816,346.197327+305.111816,346.197327+289.885193,327.990265+305.111816"
                },
                {
                    "uuid": "62a12d229a5b23507e9aad7f2d0c5383",
                    "distribution": "8.729196e-02,0,0,0,0,0,8.729196e-02,0,0,0,0,0,0,0",
                    "shape_type": "polygon",
                    "points": "318.190186+289.633789,318.190186+305.465546,338.279449+305.465546,338.279449+289.633789,318.190186+305.465546"
                },
                {
                    "uuid": "c5adaec5201e2dbd1a94b41bdfe4019a",
                    "distribution": "7.549579e-02,0,0,0,0,0,7.549579e-02,0,0,0,0,0,0,0",
                    "shape_type": "polygon",
                    "points": "308.499481+289.625702,308.499481+305.381744,328.222870+305.381744,328.222870+289.625702,308.499481+305.381744"
                },
                {
                    "uuid": "067cc578c812c4bae747baa1d76bfb01",
                    "distribution": "7.228285e-02,0,0,0,0,0,7.228285e-02,0,0,0,0,0,0,0",
                    "shape_type": "polygon",
                    "points": "335.405914+289.723511,335.405914+305.176483,354.051270+305.176483,354.051270+289.723511,335.405914+305.176483"
                },
                {
                    "uuid": "bbfb74cae95670be3608cbfc58cdc69d",
                    "distribution": "6.227075e-02,0,0,0,0,0,6.227075e-02,0,0,0,0,0,0,0",
                    "shape_type": "polygon",
                    "points": "300.128632+289.647583,300.128632+305.099060,319.119659+305.099060,319.119659+289.647583,300.128632+305.099060"
                },
                {
                    "uuid": "657d6e3fbb0ee2b2e1d874b644f56cca",
                    "distribution": "4.740240e-02,0,0,0,0,0,4.740240e-02,0,0,0,0,0,0,0",
                    "shape_type": "polygon",
                    "points": "291.204926+289.426361,291.204926+304.759277,309.882050+304.759277,309.882050+289.426361,291.204926+304.759277"
                },
                {
                    "uuid": "ec040966b625d74af2f54440efc47b87",
                    "distribution": "3.878042e-02,0,0,0,0,0,3.878042e-02,0,0,0,0,0,0,0",
                    "shape_type": "polygon",
                    "points": "399.333069+532.227234,399.333069+552.724670,420.573517+552.724670,420.573517+532.227234,399.333069+552.724670"
                },
                {
                    "uuid": "0fd705065f8098163ff242334b5d3339",
                    "distribution": "2.989528e-02,0,0,0,0,0,2.989528e-02,0,0,0,0,0,0,0",
                    "shape_type": "polygon",
                    "points": "262.662811+288.756073,262.662811+304.401306,280.659119+304.401306,280.659119+288.756073,262.662811+304.401306"
                },
                {
                    "uuid": "0e7c0b980d701b2bd99dcb2cf4526a01",
                    "distribution": "2.963368e-02,0,0,0,0,0,2.963368e-02,0,0,0,0,0,0,0",
                    "shape_type": "polygon",
                    "points": "282.027679+289.212708,282.027679+304.495117,300.386108+304.495117,300.386108+289.212708,282.027679+304.495117"
                },
                {
                    "uuid": "77c045e9451e5ef24783307600249f58",
                    "distribution": "2.759762e-02,0,0,0,0,0,2.759762e-02,0,0,0,0,0,0,0",
                    "shape_type": "polygon",
                    "points": "343.962616+288.832458,343.962616+305.672363,363.955872+305.672363,363.955872+288.832458,343.962616+305.672363"
                },
                {
                    "uuid": "92a3111e2a4f8ef867d43e43abaa3490",
                    "distribution": "1.987964e-02,0,0,0,0,0,1.987964e-02,0,0,0,0,0,0,0",
                    "shape_type": "polygon",
                    "points": "327.366974+293.049469,327.366974+311.148438,346.886292+311.148438,346.886292+293.049469,327.366974+311.148438"
                },
                {
                    "uuid": "16a85a02b0dc6a1da35db799e442942b",
                    "distribution": "1.177411e-02,0,0,0,0,0,1.177411e-02,0,0,0,0,0,0,0",
                    "shape_type": "polygon",
                    "points": "326.976440+282.296295,326.976440+302.110138,347.201874+302.110138,347.201874+282.296295,326.976440+302.110138"
                },
                {
                    "uuid": "89094c4bf18dd2ccb2695b1ed9ecce8c",
                    "distribution": "1.033212e-02,0,0,0,0,0,1.033212e-02,0,0,0,0,0,0,0",
                    "shape_type": "polygon",
                    "points": "317.674591+293.062653,317.674591+311.629913,339.029419+311.629913,339.029419+293.062653,317.674591+311.629913"
                },
                {
                    "uuid": "933d6e39462baca6f7c4aab003d2a7fa",
                    "distribution": "9.212327e-03,0,0,0,0,0,9.212327e-03,0,0,0,0,0,0,0",
                    "shape_type": "polygon",
                    "points": "307.863190+293.369720,307.863190+311.830688,328.882355+311.830688,328.882355+293.369720,307.863190+311.830688"
                },
                {
                    "uuid": "137bfce7902062b32c154406df080309",
                    "distribution": "7.059792e-03,0,0,0,0,0,7.059792e-03,0,0,0,0,0,0,0",
                    "shape_type": "polygon",
                    "points": "334.777771+293.125977,334.777771+311.455872,354.771179+311.455872,354.771179+293.125977,334.777771+311.455872"
                }
            ]
        },
        {
            "info": {
                "uuid": "50e927806eccdd5d2e35762b662ea7fb",
                "image_path": "changdian/2022-01-27/attention/normal/1PxM/MPS-ST3099R5-UBM/MP2112707A/2AI05QUM2/HJA520-22-D4/raw__MP2112707A_HJA520-22-D4_UBM_25_1_1.jpg",
                "height": 600,
                "width": 600
            },
            "instances": [
                {
                    "uuid": "42caecbc34cb80c0f049bc246ca0f5cf",
                    "distribution": "2.443003e-02,0,0,0,0,2.443003e-02,0,0,0,0,0,0,0,0",
                    "shape_type": "polygon",
                    "points": "290.627716+287.241882,290.627716+307.675629,309.058228+307.675629,309.058228+287.241882,290.627716+307.675629"
                },
                {
                    "uuid": "600e898e88208bf53639eb654d6fa964",
                    "distribution": "1.782679e-02,0,0,0,0,1.782679e-02,0,0,0,0,0,0,0,0",
                    "shape_type": "polygon",
                    "points": "290.014893+278.904877,290.014893+301.464813,309.579865+301.464813,309.579865+278.904877,290.014893+301.464813"
                },
                {
                    "uuid": "52fe75640e09c4bbb7d910a346337431",
                    "distribution": "6.600737e-02,0,0,0,0,0,6.600737e-02,0,0,0,0,0,0,0",
                    "shape_type": "polygon",
                    "points": "290.627716+287.241882,290.627716+307.675629,309.058228+307.675629,309.058228+287.241882,290.627716+307.675629"
                },
                {
                    "uuid": "91f3d98a22c39d1b1129be36ad9cd4ea",
                    "distribution": "3.911694e-02,0,0,0,0,0,3.911694e-02,0,0,0,0,0,0,0",
                    "shape_type": "polygon",
                    "points": "298.538574+286.797974,298.538574+308.383606,317.529327+308.383606,317.529327+286.797974,298.538574+308.383606"
                },
                {
                    "uuid": "32406c90e339768f8b18c5602f0817b8",
                    "distribution": "3.613145e-02,0,0,0,0,0,3.613145e-02,0,0,0,0,0,0,0",
                    "shape_type": "polygon",
                    "points": "290.014893+278.904877,290.014893+301.464813,309.579865+301.464813,309.579865+278.904877,290.014893+301.464813"
                },
                {
                    "uuid": "a48c5abaafe9e64ba6aeb7c1ca461939",
                    "distribution": "3.056465e-02,0,0,0,0,0,3.056465e-02,0,0,0,0,0,0,0",
                    "shape_type": "polygon",
                    "points": "290.446075+294.185455,290.446075+315.933807,309.371765+315.933807,309.371765+294.185455,290.446075+315.933807"
                },
                {
                    "uuid": "a1e0cd5101ebd517edd002f8d9f5aff6",
                    "distribution": "2.999133e-02,0,0,0,0,0,2.999133e-02,0,0,0,0,0,0,0",
                    "shape_type": "polygon",
                    "points": "288.839417+268.211121,288.839417+295.366302,310.482574+295.366302,310.482574+268.211121,288.839417+295.366302"
                },
                {
                    "uuid": "2d874ab12b436f33db43dcba0454cf80",
                    "distribution": "2.534057e-02,0,0,0,0,0,2.534057e-02,0,0,0,0,0,0,0",
                    "shape_type": "polygon",
                    "points": "289.473145+312.056763,289.473145+338.307587,310.436310+338.307587,310.436310+312.056763,289.473145+338.307587"
                },
                {
                    "uuid": "609635d34229643abe6553c03a385f8a",
                    "distribution": "2.469787e-02,0,0,0,0,0,2.469787e-02,0,0,0,0,0,0,0",
                    "shape_type": "polygon",
                    "points": "289.922943+302.619507,289.922943+326.777618,309.899017+326.777618,309.899017+302.619507,289.922943+326.777618"
                },
                {
                    "uuid": "19bc0f88331de7a8f553b8f339b7de8c",
                    "distribution": "2.353576e-02,0,0,0,0,0,2.353576e-02,0,0,0,0,0,0,0",
                    "shape_type": "polygon",
                    "points": "298.328705+331.971893,298.328705+359.803345,319.558044+359.803345,319.558044+331.971893,298.328705+359.803345"
                },
                {
                    "uuid": "ec5129fa8735c1294ccffab6ab5d7b2d",
                    "distribution": "2.190419e-02,0,0,0,0,0,2.190419e-02,0,0,0,0,0,0,0",
                    "shape_type": "polygon",
                    "points": "298.252228+342.944275,298.252228+368.717712,318.400635+368.717712,318.400635+342.944275,298.252228+368.717712"
                },
                {
                    "uuid": "7b677492831f9c2a62c96f1b5fb3cd2a",
                    "distribution": "2.148166e-02,0,0,0,0,0,2.148166e-02,0,0,0,0,0,0,0",
                    "shape_type": "polygon",
                    "points": "298.057648+278.340424,298.057648+302.280090,318.255524+302.280090,318.255524+278.340424,298.057648+302.280090"
                },
                {
                    "uuid": "fadc708e6bcc9896ccb8a45178567b21",
                    "distribution": "2.071967e-02,0,0,0,0,0,2.071967e-02,0,0,0,0,0,0,0",
                    "shape_type": "polygon",
                    "points": "306.894409+285.863281,306.894409+309.410980,327.902893+309.410980,327.902893+285.863281,306.894409+309.410980"
                },
                {
                    "uuid": "97fdadf459d616dd1d1bd85d629ef6c3",
                    "distribution": "2.005406e-02,0,0,0,0,0,2.005406e-02,0,0,0,0,0,0,0",
                    "shape_type": "polygon",
                    "points": "298.372498+311.624756,298.372498+338.994293,319.729828+338.994293,319.729828+311.624756,298.372498+338.994293"
                },
                {
                    "uuid": "e18a380c6d840a72401f2c5fbfb608c2",
                    "distribution": "1.936463e-02,0,0,0,0,0,1.936463e-02,0,0,0,0,0,0,0",
                    "shape_type": "polygon",
                    "points": "281.754333+287.330627,281.754333+308.145142,302.728485+308.145142,302.728485+287.330627,281.754333+308.145142"
                },
                {
                    "uuid": "e7a0b565762f006a578e8e5c6e585077",
                    "distribution": "1.890232e-02,0,0,0,0,0,1.890232e-02,0,0,0,0,0,0,0",
                    "shape_type": "polygon",
                    "points": "298.524231+293.720398,298.524231+316.669373,317.916260+316.669373,317.916260+293.720398,298.524231+316.669373"
                },
                {
                    "uuid": "276e1901660a128233baa9a4baad57d3",
                    "distribution": "1.829469e-02,0,0,0,0,0,1.829469e-02,0,0,0,0,0,0,0",
                    "shape_type": "polygon",
                    "points": "297.632599+267.310272,297.632599+296.402252,319.708099+296.402252,319.708099+267.310272,297.632599+296.402252"
                },
                {
                    "uuid": "6e1ba3c8167982377e7f7808b86702b9",
                    "distribution": "1.673711e-02,0,0,0,0,0,1.673711e-02,0,0,0,0,0,0,0",
                    "shape_type": "polygon",
                    "points": "298.466797+302.297119,298.466797+327.528625,318.910034+327.528625,318.910034+302.297119,298.466797+327.528625"
                },
                {
                    "uuid": "4c58ab58e4c7812b5ea8a34f0aeacbde",
                    "distribution": "1.579938e-02,0,0,0,0,0,1.579938e-02,0,0,0,0,0,0,0",
                    "shape_type": "polygon",
                    "points": "307.084198+341.736237,307.084198+368.318848,329.464142+368.318848,329.464142+341.736237,307.084198+368.318848"
                },
                {
                    "uuid": "14eaa355cb35a3aca0ae1bc8acc2f182",
                    "distribution": "1.548080e-02,0,0,0,0,0,1.548080e-02,0,0,0,0,0,0,0",
                    "shape_type": "polygon",
                    "points": "306.490997+276.845673,306.490997+302.788269,328.690552+302.788269,328.690552+276.845673,306.490997+302.788269"
                },
                {
                    "uuid": "2b7a2a8f0354f3ef301b543d0a2eb8ac",
                    "distribution": "1.405241e-02,0,0,0,0,0,1.405241e-02,0,0,0,0,0,0,0",
                    "shape_type": "polygon",
                    "points": "281.476654+278.425079,281.476654+300.992401,303.302338+300.992401,303.302338+278.425079,281.476654+300.992401"
                }
            ]
        },
        {
            "info": {
                "uuid": "bff6e80a1b0ad51f60ab6159a64d411f",
                "image_path": "changdian/2022-01-27/attention/normal/1PxM/MPS-SM3519ZR8-UBM/NP2142533A/2AI05BUM2/X26477-01B4/raw__X26477-01B4_X_74_Y_75_215_1.jpg",
                "height": 600,
                "width": 600
            },
            "instances": [
                {
                    "uuid": "8cd1b98498fcb67ed9717470b9650e0d",
                    "distribution": "4.889707e-02,0,0,0,4.889707e-02,0,0,0,0,0,0,0,0,0",
                    "shape_type": "polygon",
                    "points": "513.990601+47.517326,513.990601+115.508514,583.772461+115.508514,583.772461+47.517326,513.990601+115.508514"
                },
                {
                    "uuid": "132a6278853feb851e6a972a3e83bc46",
                    "distribution": "3.837996e-02,0,0,0,3.837996e-02,0,0,0,0,0,0,0,0,0",
                    "shape_type": "polygon",
                    "points": "170.402679+45.591724,170.402679+114.497490,241.913452+114.497490,241.913452+45.591724,170.402679+114.497490"
                },
                {
                    "uuid": "1da1709c9eb37d06f03113d8064e852a",
                    "distribution": "4.368331e-02,0,0,0,0,4.368331e-02,0,0,0,0,0,0,0,0",
                    "shape_type": "polygon",
                    "points": "191.649902+97.050041,191.649902+461.042358,451.452759+461.042358,451.452759+97.050041,191.649902+461.042358"
                },
                {
                    "uuid": "7bd9f7b5b7767def004961ccaf5d917a",
                    "distribution": "9.424161e-02,0,0,0,0,0,9.424161e-02,0,0,0,0,0,0,0",
                    "shape_type": "polygon",
                    "points": "191.649902+97.050041,191.649902+461.042358,451.452759+461.042358,451.452759+97.050041,191.649902+461.042358"
                },
                {
                    "uuid": "50f8cd48ef0f79460d1e0938e1e87008",
                    "distribution": "8.266689e-01,0,0,0,0,0,0,0,8.266689e-01,0,0,0,0,0",
                    "shape_type": "polygon",
                    "points": "265.528412+265.082672,265.528412+333.444336,335.492004+333.444336,335.492004+265.082672,265.528412+333.444336"
                },
                {
                    "uuid": "4606952e07086fde7dfe219be2953852",
                    "distribution": "8.216871e-01,0,0,0,0,0,0,0,8.216871e-01,0,0,0,0,0",
                    "shape_type": "polygon",
                    "points": "171.299957+46.824162,171.299957+114.927826,242.310120+114.927826,242.310120+46.824162,171.299957+114.927826"
                },
                {
                    "uuid": "5eb6c5eac9fb682eb14ac17b6ae4a196",
                    "distribution": "7.667294e-01,0,0,0,0,0,0,0,7.667294e-01,0,0,0,0,0",
                    "shape_type": "polygon",
                    "points": "422.100006+331.460602,422.100006+399.692627,490.562866+399.692627,490.562866+331.460602,422.100006+399.692627"
                },
                {
                    "uuid": "647fda2569cbfb8a295437726c418725",
                    "distribution": "6.674890e-01,0,0,0,0,0,0,0,6.674890e-01,0,0,0,0,0",
                    "shape_type": "polygon",
                    "points": "515.425842+47.617622,515.425842+115.584045,584.998413+115.584045,584.998413+47.617622,515.425842+115.584045"
                },
                {
                    "uuid": "729e36bc6ccafbfc3aad392a44799c6d",
                    "distribution": "1.997195e-01,0,0,0,0,0,0,0,1.997195e-01,0,0,0,0,0",
                    "shape_type": "polygon",
                    "points": "0.000000+333.810028,0.000000+398.639099,39.228428+398.639099,39.228428+333.810028,0.000000+398.639099"
                },
                {
                    "uuid": "14460842d0f8ab8506791572740c5178",
                    "distribution": "6.326669e-02,0,0,0,0,0,0,0,0,6.326669e-02,0,0,0,0",
                    "shape_type": "polygon",
                    "points": "185.781830+92.557632,185.781830+463.311798,469.793762+463.311798,469.793762+92.557632,185.781830+463.311798"
                }
            ]
        }
    ],
    "class_dict": [
        {
            "class_id": 0,
            "class_name": "NG",
            "parent": null
        },
        {
            "class_id": 1,
            "class_name": "MAB",
            "parent": "NG",
            "alias": "Misalignment Bump"
        },
        {
            "class_id": 2,
            "class_name": "SBD",
            "parent": "NG",
            "alias": "Small Black Dot"
        },
        {
            "class_id": 3,
            "class_name": "BD",
            "parent": "NG",
            "alias": "Bump Damage"
        },
        {
            "class_id": 4,
            "class_name": "AUR",
            "parent": "NG",
            "alias": "Au Residue"
        },
        {
            "class_id": 5,
            "class_name": "BDG",
            "parent": "NG",
            "alias": "Bridging"
        },
        {
            "class_id": 6,
            "class_name": "FM",
            "parent": "NG",
            "alias": "Fororeign Material"
        },
        {
            "class_id": 7,
            "class_name": "FM_Blank",
            "parent": "NG",
            "alias": "Fororeign Material"
        },
        {
            "class_id": 8,
            "class_name": "BS_White",
            "parent": "NG",
            "alias": "Bump Strach"
        },
        {
            "class_id": 9,
            "class_name": "SN_R",
            "parent": "NG",
            "alias": "Sn residue"
        },
        {
            "class_id": 10,
            "class_name": "IBT",
            "parent": "NG",
            "alias": "Irregular Bump"
        },
        {
            "class_id": 11,
            "class_name": "MB",
            "parent": "NG",
            "alias": "Missing Bump"
        },
        {
            "class_id": 12,
            "class_name": "IB",
            "parent": "NG",
            "alias": "Incomplete Bump"
        },
        {
            "class_id": 13,
            "class_name": "Others",
            "parent": "NG",
            "alias": "CRK,PR_R,PIB,RSS,RDLS,EB,SS,MS,INKD,IBC,PAD"
        }
    ]
}